UUMCdata/CausalModel.py
UUMCdata/ChecksErrors.py
UUMCdata/Data.py
UUMCdata/__init__.py
uumcdata-0.0.dist-info/licenses/LICENSE
uumcdata-0.0.dist-info/WHEEL
uumcdata-0.0.dist-info/METADATA
uumcdata-0.0.dist-info/RECORD
