Metadata-Version: 2.4
Name: UUMCdata
Version: 0.0
Summary: Unitless, Unrestricted, Markov-Consistent Random SCM and Data Generation.
Keywords: benchmark,data generation,causal discovery
Author: Rebecca J. Herman
Classifier: Programming Language :: Python :: 3
Classifier: Topic :: Scientific/Engineering
Classifier: Topic :: Scientific/Engineering :: Mathematics
Classifier: Topic :: Scientific/Engineering :: Artificial Intelligence
Classifier: License :: OSI Approved :: GNU General Public License (GPL)
Classifier: Intended Audience :: Science/Research
License-File: LICENSE
Requires-Dist: numpy
Requires-Dist: mpmath
Requires-Dist: sympy
Requires-Dist: matplotlib
Requires-Dist: daosim
Requires-Dist: seaborn
Requires-Dist: pandas
